docs/docs/index.md
docs/docs/usage-cli.md
docs/docs/usage-client.md
docs/docs/utilities.md
justupdate/__init__.py
justupdate/cli/__init__.py
justupdate/cli/commands.py
justupdate/cli/helper.py
justupdate/client/__init__.py
justupdate/client/client.py
justupdate/client/exceptions.py
justupdate/core/__init__.py
justupdate/core/base.py
justupdate/core/config.py
justupdate/core/data_manager.py
justupdate/core/executor.py
justupdate/repo/__init__.py
justupdate/repo/builder.py
justupdate/repo/committer.py
justupdate/repo/metadata.py
justupdate/repo/template.py
justupdate/repo/uploader.py
justupdate/repo/version.py
justupdate/templates/MAC/scripts/postinstall.sh
justupdate/templates/MAC/scripts/preinstall.sh
justupdate/templates/MAC/template.plist
justupdate/templates/README.md
justupdate/templates/win/template.nsi
README.md
justupdate-1.3.10.dist-info/entry_points.txt
justupdate-1.3.10.dist-info/LICENSE
justupdate-1.3.10.dist-info/WHEEL
justupdate-1.3.10.dist-info/METADATA
justupdate-1.3.10.dist-info/RECORD
